Application/Main.py
Application/_init_.py
cbs_sdk-1.0.dist-info/METADATA
cbs_sdk-1.0.dist-info/WHEEL
cbs_sdk-1.0.dist-info/top_level.txt
cbs_sdk-1.0.dist-info/RECORD
