Metadata-Version: 2.1
Name: cbs-sdk
Version: 1.0
Summary: This is a service of cbs sdk
Home-page: UNKNOWN
Author: chinabanksoft
Author-email: andreas@drqueue.org
License: chinabanksoft
Keywords: cbs sdk
Platform: UNKNOWN
Classifier: Development Status :: 3 - Alpha
Classifier: Topic :: Utilities
Classifier: License :: OSI Approved :: GNU General Public License (GPL)
Requires-Dist: redis (>=3.2.1)
Requires-Dist: pymongo (>=3.7.2)
Requires-Dist: tornado (>=6.0.2)
Requires-Dist: motor (>=2.0.0)
Requires-Dist: setuptools (>=39.1.0)
